LICENCE.md
MANIFEST.in
README.md
setup.py
opengenomebrowser_tools/__init__.py
opengenomebrowser_tools/download_ncbi_genome.py
opengenomebrowser_tools/folder_looper.py
opengenomebrowser_tools/genbank_to_fasta.py
opengenomebrowser_tools/import_genome.py
opengenomebrowser_tools/import_genome2.py
opengenomebrowser_tools/import_orthofinder.py
opengenomebrowser_tools/init_folder_structure.py
opengenomebrowser_tools/init_orthofinder.py
opengenomebrowser_tools/metadata_schemas.py
opengenomebrowser_tools/parse_busco.py
opengenomebrowser_tools/reindex_assembly.py
opengenomebrowser_tools/rename_custom_annotations.py
opengenomebrowser_tools/rename_eggnog.py
opengenomebrowser_tools/rename_fasta.py
opengenomebrowser_tools/rename_genbank.py
opengenomebrowser_tools/rename_gff.py
opengenomebrowser_tools/update_folder_structure.py
opengenomebrowser_tools/utils.py
opengenomebrowser_tools.egg-info/PKG-INFO
opengenomebrowser_tools.egg-info/SOURCES.txt
opengenomebrowser_tools.egg-info/dependency_links.txt
opengenomebrowser_tools.egg-info/entry_points.txt
opengenomebrowser_tools.egg-info/requires.txt
opengenomebrowser_tools.egg-info/top_level.txt
opengenomebrowser_tools/data/COG_categories.json
opengenomebrowser_tools/data/annotations.json