Metadata-Version: 2.1
Name: opengenomebrowser-tools
Version: 0.0.9
Summary: Set of scripts to aid OpenGenomeBrowser administrators import data
Home-page: https://github.com/opengenomebrowser/opengenomebrowser-tools
Author: Thomas Roder
Author-email: roder.thomas@gmail.com
License: MIT
Classifier: License :: OSI Approved :: MIT License
Classifier: Programming Language :: Python :: 3
Classifier: Programming Language :: Python :: 3.9
License-File: LICENCE.md
